lightning_habana/__about__.py
lightning_habana/__init__.py
lightning_habana/fabric/__init__.py
lightning_habana/fabric/accelerator.py
lightning_habana/fabric/plugins/__init__.py
lightning_habana/fabric/plugins/fsdp_precision.py
lightning_habana/fabric/plugins/io_plugin.py
lightning_habana/fabric/plugins/precision.py
lightning_habana/fabric/strategies/__init__.py
lightning_habana/fabric/strategies/ddp.py
lightning_habana/fabric/strategies/fsdp.py
lightning_habana/fabric/strategies/parallel.py
lightning_habana/fabric/strategies/single.py
lightning_habana/pytorch/__init__.py
lightning_habana/pytorch/accelerator.py
lightning_habana/pytorch/datamodule/__init__.py
lightning_habana/pytorch/datamodule/datamodule.py
lightning_habana/pytorch/datamodule/utils.py
lightning_habana/pytorch/datamodule/dataloaders/__init__.py
lightning_habana/pytorch/datamodule/dataloaders/resnet_media_pipe.py
lightning_habana/pytorch/plugins/__init__.py
lightning_habana/pytorch/plugins/deepspeed_precision.py
lightning_habana/pytorch/plugins/fsdp_precision.py
lightning_habana/pytorch/plugins/io_plugin.py
lightning_habana/pytorch/plugins/precision.py
lightning_habana/pytorch/plugins/quant_config/fp8/maxabs_measure.json
lightning_habana/pytorch/plugins/quant_config/fp8/maxabs_quant.json
lightning_habana/pytorch/profiler/__init__.py
lightning_habana/pytorch/profiler/profiler.py
lightning_habana/pytorch/strategies/__init__.py
lightning_habana/pytorch/strategies/ddp.py
lightning_habana/pytorch/strategies/deepspeed.py
lightning_habana/pytorch/strategies/fsdp.py
lightning_habana/pytorch/strategies/parallel.py
lightning_habana/pytorch/strategies/single.py
lightning_habana/utils/__init__.py
lightning_habana/utils/hpu_distributed.py
lightning_habana/utils/imports.py
lightning_habana/utils/resources.py
lightning_habana-1.6.0.data/data/jsons/maxabs_measure.json
lightning_habana-1.6.0.data/data/jsons/maxabs_quant.json
lightning_habana-1.6.0.dist-info/LICENSE
lightning_habana-1.6.0.dist-info/METADATA
lightning_habana-1.6.0.dist-info/WHEEL
lightning_habana-1.6.0.dist-info/top_level.txt
lightning_habana-1.6.0.dist-info/RECORD
