Metadata-Version: 2.1
Name: lightning-habana
Version: 1.6.0
Summary: Lightning support for Intel Habana accelerators
Home-page: https://github.com/Lightning-AI/lightning-habana
Download-URL: https://github.com/Lightning-AI/lightning-habana
Author: Lightning-AI et al.
Author-email: name@lightning.ai
License: Apache-2.0
Project-URL: Bug Tracker, https://github.com/Lightning-AI/lightning-habana/issues
Project-URL: Documentation, https://lightning-habana.rtfd.io/en/latest/
Project-URL: Source Code, https://github.com/Lightning-AI/lightning-habana
Keywords: deep learning,pytorch,AI
Classifier: Environment :: Console
Classifier: Natural Language :: English
Classifier: Development Status :: 4 - Beta
Classifier: Intended Audience :: Developers
Classifier: Topic :: Scientific/Engineering :: Artificial Intelligence
Classifier: Topic :: Scientific/Engineering :: Information Analysis
Classifier: License :: OSI Approved :: Apache Software License
Classifier: Operating System :: OS Independent
Classifier: Programming Language :: Python :: 3
Classifier: Programming Language :: Python :: 3.8
Classifier: Programming Language :: Python :: 3.9
Classifier: Programming Language :: Python :: 3.10
Classifier: Programming Language :: Python :: 3.11
Requires-Python: >=3.8
License-File: LICENSE
Requires-Dist: lightning-utilities >=0.7.0
Provides-Extra: base
Requires-Dist: lightning-utilities >=0.7.0 ; extra == 'base'
Provides-Extra: examples
Requires-Dist: jsonargparse[signatures] ; extra == 'examples'
Provides-Extra: lightning
Requires-Dist: lightning >=2.3.0 ; extra == 'lightning'
Provides-Extra: pytorch-lightning
Requires-Dist: pytorch-lightning >=2.3.0 ; extra == 'pytorch-lightning'
Provides-Extra: typing
Requires-Dist: mypy ==1.10.1 ; extra == 'typing'
Requires-Dist: pytorch-lightning ==2.3.0 ; extra == 'typing'
